icsDataValidation/configuration.py
icsDataValidation/main.py
icsDataValidation/connection_setups/__init__.py
icsDataValidation/connection_setups/azure_connection_setup.py
icsDataValidation/connection_setups/databricks_connection_setup.py
icsDataValidation/connection_setups/exasol_connection_setup.py
icsDataValidation/connection_setups/oracle_connection_setup.py
icsDataValidation/connection_setups/snowflake_connection_setup.py
icsDataValidation/connection_setups/sqlserver_connection_setup.py
icsDataValidation/connection_setups/teradata_connection_setup.py
icsDataValidation/core/__init__.py
icsDataValidation/core/database_objects.py
icsDataValidation/core/object_comparison.py
icsDataValidation/input_parameters/__init__.py
icsDataValidation/input_parameters/testing_tool_params.py
icsDataValidation/output_parameters/__init__.py
icsDataValidation/output_parameters/result_params.py
icsDataValidation/services/__init__.py
icsDataValidation/services/comparison_service.py
icsDataValidation/services/initialization_service.py
icsDataValidation/services/result_service.py
icsDataValidation/services/system_service.py
icsDataValidation/services/testset_service.py
icsDataValidation/services/database_services/__init__.py
icsDataValidation/services/database_services/azure_service.py
icsDataValidation/services/database_services/databricks_hive_metastore_service.py
icsDataValidation/services/database_services/databricks_unity_catalog_service.py
icsDataValidation/services/database_services/exasol_service.py
icsDataValidation/services/database_services/oracle_service.py
icsDataValidation/services/database_services/snowflake_service.py
icsDataValidation/services/database_services/sqlserver_service.py
icsDataValidation/services/database_services/teradata_service.py
icsDataValidation/utils/__init__.py
icsDataValidation/utils/file_util.py
icsDataValidation/utils/logger_util.py
icsDataValidation/utils/pandas_util.py
icsDataValidation/utils/parallelization_util.py
icsdatavalidation-1.0.430.dist-info/METADATA
icsdatavalidation-1.0.430.dist-info/WHEEL
icsdatavalidation-1.0.430.dist-info/top_level.txt
icsdatavalidation-1.0.430.dist-info/RECORD
