Metadata-Version: 2.4
Name: icsDataValidation
Version: 1.0.430
Summary: Add your description here
Author-email: initions <ICSMC_EXT_PYPIORG@accenture.com>
License: MIT
Requires-Python: >=3.11
Requires-Dist: azure-storage-blob==12.13.1
Requires-Dist: boto3==1.26.154
Requires-Dist: cloe-util-snowflake-connector==1.0.5
Requires-Dist: databricks-sdk==0.29.0
Requires-Dist: databricks-sql-connector==3.0.1
Requires-Dist: numpy==1.26.3
Requires-Dist: oracledb==2.5.0
Requires-Dist: pandas==2.2.2
Requires-Dist: pyexasol==0.24.0
Requires-Dist: pyodbc
Requires-Dist: python-dotenv>=1.0.1
Requires-Dist: teradatasql==17.20.0.10
